---- General Information ----

Version:		52.0 (Major.minor) [jdk version 1.8]
Constant pool count:	136
Access flags:		0x0021 [super, public]
This class:		cp index #47 <sketch/Sketch>
Super class:		cp index #48 <java/lang/Object>
Interfaces count:	2
Fields count:		8
Methods count:		5
Attributes count:	2

---- Constant Pool ----

	#1: Methodref (tag = 10)
		class_index: cp index #48 <java/lang/Object>
		name_and_type_index: cp index #96
		name_and_type.name_index: cp index #77 <<init>>
		name_and_type.descriptor_index: cp index #78 <()V>

	#2: Long (tag = 5)
		High Bytes: 0x00150000
		Low  Bytes: 0x00000000
		Long Value: 5910974510923776

	#4: Fieldref (tag = 9)
		class_index: cp index #47 <sketch/Sketch>
		name_and_type_index: cp index #97
		name_and_type.name_index: cp index #64 <long_member>
		name_and_type.descriptor_index: cp index #65 <J>

	#5: String (tag = 8)
		string_index: cp index #98
		String Length: 5
		ASCII: ?????
		UTF-8: πφμβƒ

	#6: Fieldref (tag = 9)
		class_index: cp index #47 <sketch/Sketch>
		name_and_type_index: cp index #99
		name_and_type.name_index: cp index #67 <??????>
		name_and_type.descriptor_index: cp index #68 <Ljava/lang/String;>

	#7: Fieldref (tag = 9)
		class_index: cp index #47 <sketch/Sketch>
		name_and_type_index: cp index #100
		name_and_type.name_index: cp index #69 <bool_member>
		name_and_type.descriptor_index: cp index #70 <Z>

	#8: Class (tag = 7)
		name_index: cp index #101 <[[I>

	#9: Class (tag = 7)
		name_index: cp index #58 <[I>

	#10: Fieldref (tag = 9)
		class_index: cp index #47 <sketch/Sketch>
		name_and_type_index: cp index #102
		name_and_type.name_index: cp index #73 <matrix3d>
		name_and_type.descriptor_index: cp index #74 <[[[I>

	#11: Class (tag = 7)
		name_index: cp index #103 <[D>

	#12: Double (tag = 6)
		High Bytes:   0x405EDD2F
		Low  Bytes:   0x1A9FBE77
		Double Value: 1.234560e+002

	#14: Double (tag = 6)
		High Bytes:   0xC0847291
		Low  Bytes:   0x6872B021
		Double Value: -6.543210e+002

	#16: Double (tag = 6)
		High Bytes:   0x41CD6F34
		Low  Bytes:   0x588FCD6F
		Double Value: 9.876543e+008

	#18: Class (tag = 7)
		name_index: cp index #104 <java/lang/Double>

	#19: Double (tag = 6)
		High Bytes:   0x7FEFFFFF
		Low  Bytes:   0xFFFFFFFF
		Double Value: 1.797693e+308

	#21: Double (tag = 6)
		High Bytes:   0x00000000
		Low  Bytes:   0x00000001
		Double Value: 4.940656e-324

	#23: Double (tag = 6)
		High Bytes:   0x00100000
		Low  Bytes:   0x00000000
		Double Value: 2.225074e-308

	#25: Double (tag = 6)
		High Bytes:   0x7FF80000
		Low  Bytes:   0x00000000
		Double Value: nan

	#27: Double (tag = 6)
		High Bytes:   0x7FF00000
		Low  Bytes:   0x00000000
		Double Value: inf

	#29: Double (tag = 6)
		High Bytes:   0xFFF00000
		Low  Bytes:   0x00000000
		Double Value: -inf

	#31: Fieldref (tag = 9)
		class_index: cp index #47 <sketch/Sketch>
		name_and_type_index: cp index #105
		name_and_type.name_index: cp index #75 <matrix2d>
		name_and_type.descriptor_index: cp index #76 <[[D>

	#32: Class (tag = 7)
		name_index: cp index #106 <sketch/Sketch$NestedClass>

	#33: Methodref (tag = 10)
		class_index: cp index #32 <sketch/Sketch$NestedClass>
		name_and_type_index: cp index #107
		name_and_type.name_index: cp index #77 <<init>>
		name_and_type.descriptor_index: cp index #127 <(Lsketch/Sketch;)V>

	#34: InterfaceMethodref (tag = 11)
		class_index: cp index #55 <sketch/Sketch$Test>
		name_and_type_index: cp index #108
		name_and_type.name_index: cp index #128 <method1>
		name_and_type.descriptor_index: cp index #129 <([I)I>

	#35: Fieldref (tag = 9)
		class_index: cp index #47 <sketch/Sketch>
		name_and_type_index: cp index #109
		name_and_type.name_index: cp index #66 <long_static_value>
		name_and_type.descriptor_index: cp index #65 <J>

	#36: Long (tag = 5)
		High Bytes: 0x00000000
		Low  Bytes: 0x00000005
		Long Value: 5

	#38: String (tag = 8)
		string_index: cp index #110
		String Length: 3
		ASCII: ola

	#39: Class (tag = 7)
		name_index: cp index #111 <java/lang/String>

	#40: Fieldref (tag = 9)
		class_index: cp index #112 <java/lang/System>
		name_and_type_index: cp index #113
		name_and_type.name_index: cp index #131 <out>
		name_and_type.descriptor_index: cp index #132 <Ljava/io/PrintStream;>

	#41: Methodref (tag = 10)
		class_index: cp index #114 <java/io/PrintStream>
		name_and_type_index: cp index #115
		name_and_type.name_index: cp index #134 <println>
		name_and_type.descriptor_index: cp index #135 <(Ljava/lang/String;)V>

	#42: Class (tag = 7)
		name_index: cp index #116 <[[Ljava/lang/String;>

	#43: Class (tag = 7)
		name_index: cp index #117 <java/lang/ArithmeticException>

	#44: Fieldref (tag = 9)
		class_index: cp index #47 <sketch/Sketch>
		name_and_type_index: cp index #118
		name_and_type.name_index: cp index #57 <values>
		name_and_type.descriptor_index: cp index #58 <[I>

	#45: Long (tag = 5)
		High Bytes: 0x015EE2A3
		Low  Bytes: 0x21CE7D15
		Long Value: 98765432123456789

	#47: Class (tag = 7)
		name_index: cp index #119 <sketch/Sketch>

	#48: Class (tag = 7)
		name_index: cp index #120 <java/lang/Object>

	#49: Class (tag = 7)
		name_index: cp index #121 <java/util/EventListener>

	#50: Class (tag = 7)
		name_index: cp index #122 <java/util/RandomAccess>

	#51: Utf8 (tag = 1)
		Byte Count: 11
		Length: 11
		ASCII Characters: NestedClass

	#52: Utf8 (tag = 1)
		Byte Count: 12
		Length: 12
		ASCII Characters: InnerClasses

	#53: Class (tag = 7)
		name_index: cp index #123 <sketch/Sketch$AnotherInterface>

	#54: Utf8 (tag = 1)
		Byte Count: 16
		Length: 16
		ASCII Characters: AnotherInterface

	#55: Class (tag = 7)
		name_index: cp index #124 <sketch/Sketch$Test>

	#56: Utf8 (tag = 1)
		Byte Count: 4
		Length: 4
		ASCII Characters: Test

	#57: Utf8 (tag = 1)
		Byte Count: 6
		Length: 6
		ASCII Characters: values

	#58: Utf8 (tag = 1)
		Byte Count: 2
		Length: 2
		ASCII Characters: [I

	#59: Utf8 (tag = 1)
		Byte Count: 12
		Length: 12
		ASCII Characters: float_member

	#60: Utf8 (tag = 1)
		Byte Count: 1
		Length: 1
		ASCII Characters: F

	#61: Utf8 (tag = 1)
		Byte Count: 10
		Length: 10
		ASCII Characters: Deprecated

	#62: Utf8 (tag = 1)
		Byte Count: 25
		Length: 25
		ASCII Characters: RuntimeVisibleAnnotations

	#63: Utf8 (tag = 1)
		Byte Count: 22
		Length: 22
		ASCII Characters: Ljava/lang/Deprecated;

	#64: Utf8 (tag = 1)
		Byte Count: 11
		Length: 11
		ASCII Characters: long_member

	#65: Utf8 (tag = 1)
		Byte Count: 1
		Length: 1
		ASCII Characters: J

	#66: Utf8 (tag = 1)
		Byte Count: 17
		Length: 17
		ASCII Characters: long_static_value

	#67: Utf8 (tag = 1)
		Byte Count: 12
		Length: 6
		ASCII Characters: ??????
		UTF-8 Characters: πφμβƒé

	#68: Utf8 (tag = 1)
		Byte Count: 18
		Length: 18
		ASCII Characters: Ljava/lang/String;

	#69: Utf8 (tag = 1)
		Byte Count: 11
		Length: 11
		ASCII Characters: bool_member

	#70: Utf8 (tag = 1)
		Byte Count: 1
		Length: 1
		ASCII Characters: Z

	#71: Utf8 (tag = 1)
		Byte Count: 13
		Length: 13
		ASCII Characters: ConstantValue

	#72: Integer (tag = 3)
		Bytes: 0x00000001
		Value: 1

	#73: Utf8 (tag = 1)
		Byte Count: 8
		Length: 8
		ASCII Characters: matrix3d

	#74: Utf8 (tag = 1)
		Byte Count: 4
		Length: 4
		ASCII Characters: [[[I

	#75: Utf8 (tag = 1)
		Byte Count: 8
		Length: 8
		ASCII Characters: matrix2d

	#76: Utf8 (tag = 1)
		Byte Count: 3
		Length: 3
		ASCII Characters: [[D

	#77: Utf8 (tag = 1)
		Byte Count: 6
		Length: 6
		ASCII Characters: <init>

	#78: Utf8 (tag = 1)
		Byte Count: 3
		Length: 3
		ASCII Characters: ()V

	#79: Utf8 (tag = 1)
		Byte Count: 4
		Length: 4
		ASCII Characters: Code

	#80: Utf8 (tag = 1)
		Byte Count: 15
		Length: 15
		ASCII Characters: LineNumberTable

	#81: Utf8 (tag = 1)
		Byte Count: 8
		Length: 8
		ASCII Characters: mymethod

	#82: Utf8 (tag = 1)
		Byte Count: 5
		Length: 5
		ASCII Characters: (IJ)V

	#83: Utf8 (tag = 1)
		Byte Count: 6
		Length: 6
		ASCII Characters: add_10

	#84: Utf8 (tag = 1)
		Byte Count: 5
		Length: 5
		ASCII Characters: (IF)J

	#85: Utf8 (tag = 1)
		Byte Count: 10
		Length: 10
		ASCII Characters: Exceptions

	#86: Class (tag = 7)
		name_index: cp index #125 <java/lang/Error>

	#87: Utf8 (tag = 1)
		Byte Count: 4
		Length: 4
		ASCII Characters: main

	#88: Utf8 (tag = 1)
		Byte Count: 22
		Length: 22
		ASCII Characters: ([Ljava/lang/String;)V

	#89: Utf8 (tag = 1)
		Byte Count: 13
		Length: 13
		ASCII Characters: StackMapTable

	#90: Class (tag = 7)
		name_index: cp index #120 <java/lang/Object>

	#91: Class (tag = 7)
		name_index: cp index #126 <[Ljava/lang/String;>

	#92: Class (tag = 7)
		name_index: cp index #117 <java/lang/ArithmeticException>

	#93: Utf8 (tag = 1)
		Byte Count: 8
		Length: 8
		ASCII Characters: <clinit>

	#94: Utf8 (tag = 1)
		Byte Count: 10
		Length: 10
		ASCII Characters: SourceFile

	#95: Utf8 (tag = 1)
		Byte Count: 11
		Length: 11
		ASCII Characters: Sketch.java

	#96: NameAndType (tag = 12)
		name_index: cp index #77 <<init>>
		descriptor_index: cp index #78 <()V>

	#97: NameAndType (tag = 12)
		name_index: cp index #64 <long_member>
		descriptor_index: cp index #65 <J>

	#98: Utf8 (tag = 1)
		Byte Count: 10
		Length: 5
		ASCII Characters: ?????
		UTF-8 Characters: πφμβƒ

	#99: NameAndType (tag = 12)
		name_index: cp index #67 <??????>
		descriptor_index: cp index #68 <Ljava/lang/String;>

	#100: NameAndType (tag = 12)
		name_index: cp index #69 <bool_member>
		descriptor_index: cp index #70 <Z>

	#101: Utf8 (tag = 1)
		Byte Count: 3
		Length: 3
		ASCII Characters: [[I

	#102: NameAndType (tag = 12)
		name_index: cp index #73 <matrix3d>
		descriptor_index: cp index #74 <[[[I>

	#103: Utf8 (tag = 1)
		Byte Count: 2
		Length: 2
		ASCII Characters: [D

	#104: Utf8 (tag = 1)
		Byte Count: 16
		Length: 16
		ASCII Characters: java/lang/Double

	#105: NameAndType (tag = 12)
		name_index: cp index #75 <matrix2d>
		descriptor_index: cp index #76 <[[D>

	#106: Utf8 (tag = 1)
		Byte Count: 25
		Length: 25
		ASCII Characters: sketch/Sketch$NestedClass

	#107: NameAndType (tag = 12)
		name_index: cp index #77 <<init>>
		descriptor_index: cp index #127 <(Lsketch/Sketch;)V>

	#108: NameAndType (tag = 12)
		name_index: cp index #128 <method1>
		descriptor_index: cp index #129 <([I)I>

	#109: NameAndType (tag = 12)
		name_index: cp index #66 <long_static_value>
		descriptor_index: cp index #65 <J>

	#110: Utf8 (tag = 1)
		Byte Count: 3
		Length: 3
		ASCII Characters: ola

	#111: Utf8 (tag = 1)
		Byte Count: 16
		Length: 16
		ASCII Characters: java/lang/String

	#112: Class (tag = 7)
		name_index: cp index #130 <java/lang/System>

	#113: NameAndType (tag = 12)
		name_index: cp index #131 <out>
		descriptor_index: cp index #132 <Ljava/io/PrintStream;>

	#114: Class (tag = 7)
		name_index: cp index #133 <java/io/PrintStream>

	#115: NameAndType (tag = 12)
		name_index: cp index #134 <println>
		descriptor_index: cp index #135 <(Ljava/lang/String;)V>

	#116: Utf8 (tag = 1)
		Byte Count: 20
		Length: 20
		ASCII Characters: [[Ljava/lang/String;

	#117: Utf8 (tag = 1)
		Byte Count: 29
		Length: 29
		ASCII Characters: java/lang/ArithmeticException

	#118: NameAndType (tag = 12)
		name_index: cp index #57 <values>
		descriptor_index: cp index #58 <[I>

	#119: Utf8 (tag = 1)
		Byte Count: 13
		Length: 13
		ASCII Characters: sketch/Sketch

	#120: Utf8 (tag = 1)
		Byte Count: 16
		Length: 16
		ASCII Characters: java/lang/Object

	#121: Utf8 (tag = 1)
		Byte Count: 23
		Length: 23
		ASCII Characters: java/util/EventListener

	#122: Utf8 (tag = 1)
		Byte Count: 22
		Length: 22
		ASCII Characters: java/util/RandomAccess

	#123: Utf8 (tag = 1)
		Byte Count: 30
		Length: 30
		ASCII Characters: sketch/Sketch$AnotherInterface

	#124: Utf8 (tag = 1)
		Byte Count: 18
		Length: 18
		ASCII Characters: sketch/Sketch$Test

	#125: Utf8 (tag = 1)
		Byte Count: 15
		Length: 15
		ASCII Characters: java/lang/Error

	#126: Utf8 (tag = 1)
		Byte Count: 19
		Length: 19
		ASCII Characters: [Ljava/lang/String;

	#127: Utf8 (tag = 1)
		Byte Count: 18
		Length: 18
		ASCII Characters: (Lsketch/Sketch;)V

	#128: Utf8 (tag = 1)
		Byte Count: 7
		Length: 7
		ASCII Characters: method1

	#129: Utf8 (tag = 1)
		Byte Count: 5
		Length: 5
		ASCII Characters: ([I)I

	#130: Utf8 (tag = 1)
		Byte Count: 16
		Length: 16
		ASCII Characters: java/lang/System

	#131: Utf8 (tag = 1)
		Byte Count: 3
		Length: 3
		ASCII Characters: out

	#132: Utf8 (tag = 1)
		Byte Count: 21
		Length: 21
		ASCII Characters: Ljava/io/PrintStream;

	#133: Utf8 (tag = 1)
		Byte Count: 19
		Length: 19
		ASCII Characters: java/io/PrintStream

	#134: Utf8 (tag = 1)
		Byte Count: 7
		Length: 7
		ASCII Characters: println

	#135: Utf8 (tag = 1)
		Byte Count: 21
		Length: 21
		ASCII Characters: (Ljava/lang/String;)V

---- Interfaces implemented by the class ----

	Interface #1: cp index #49 <java/util/EventListener>
	Interface #2: cp index #50 <java/util/RandomAccess>

---- Fields ----

	Field #1:

		name_index:       cp index #57 <values>
		descriptor_index: cp index #58 <[I>
		access_flags:     0x001A [private, static, final]
		attributes_count: 0


	Field #2:

		name_index:       cp index #59 <float_member>
		descriptor_index: cp index #60 <F>
		access_flags:     0x0001 [public]
		attributes_count: 2

		Field Attribute #1 - Deprecated:
			This element is marked as deprecated and should no longer be used.

		Field Attribute #2 - RuntimeVisibleAnnotations:
			Attribute not implemented and ignored.


	Field #3:

		name_index:       cp index #64 <long_member>
		descriptor_index: cp index #65 <J>
		access_flags:     0x0001 [public]
		attributes_count: 0


	Field #4:

		name_index:       cp index #66 <long_static_value>
		descriptor_index: cp index #65 <J>
		access_flags:     0x0009 [public, static]
		attributes_count: 0


	Field #5:

		name_index:       cp index #67 <??????>
		descriptor_index: cp index #68 <Ljava/lang/String;>
		access_flags:     0x0002 [private]
		attributes_count: 0


	Field #6:

		name_index:       cp index #69 <bool_member>
		descriptor_index: cp index #70 <Z>
		access_flags:     0x0014 [protected, final]
		attributes_count: 1

		Field Attribute #1 - ConstantValue:
			constantvalue_index: #72 <1>


	Field #7:

		name_index:       cp index #73 <matrix3d>
		descriptor_index: cp index #74 <[[[I>
		access_flags:     0x0002 [private]
		attributes_count: 0


	Field #8:

		name_index:       cp index #75 <matrix2d>
		descriptor_index: cp index #76 <[[D>
		access_flags:     0x0001 [public]
		attributes_count: 0


---- Methods ----

	Method #1:

		name_index:        cp index #77 <<init>>
		descriptor_index:  cp index #78 <()V>
		access_flags:      0x0001 [public]
		attribute_count:   1

		Method Attribute #1 - Code:

			max_stack: 11, max_locals: 1, code_length: 184
			exception_table_length: 0, attribute_count: 1

			Code:	Offset	Mnemonic	Parameters
				0	aload_0
				1	invokespecial	cp index #1 (Method java/lang/Object.<init>, descriptor: ()V)
				4	aload_0
				5	ldc2_w		cp index #5 (long: 5910974510923776)
				8	putfield	cp index #4 (Field sketch/Sketch.long_member, descriptor: J)
				11	aload_0
				12	ldc		cp index #12 (string: ?????)
				14	putfield	cp index #6 (Field sketch/Sketch.??????, descriptor: Ljava/lang/String;)
				17	aload_0
				18	iconst_1
				19	putfield	cp index #7 (Field sketch/Sketch.bool_member, descriptor: Z)
				22	aload_0
				23	iconst_2
				24	anewarray	cp index #8 (class: [[I)
				27	dup
				28	iconst_0
				29	iconst_2
				30	anewarray	cp index #9 (class: [I)
				33	dup
				34	iconst_0
				35	iconst_2
				36	newarray	10 (array of int)
				38	dup
				39	iconst_0
				40	iconst_1
				41	iastore
				42	dup
				43	iconst_1
				44	iconst_2
				45	iastore
				46	aastore
				47	dup
				48	iconst_1
				49	iconst_2
				50	newarray	10 (array of int)
				52	dup
				53	iconst_0
				54	iconst_3
				55	iastore
				56	dup
				57	iconst_1
				58	iconst_4
				59	iastore
				60	aastore
				61	aastore
				62	dup
				63	iconst_1
				64	iconst_2
				65	anewarray	cp index #9 (class: [I)
				68	dup
				69	iconst_0
				70	iconst_2
				71	newarray	10 (array of int)
				73	dup
				74	iconst_0
				75	iconst_5
				76	iastore
				77	dup
				78	iconst_1
				79	bipush		6
				81	iastore
				82	aastore
				83	dup
				84	iconst_1
				85	iconst_2
				86	newarray	10 (array of int)
				88	dup
				89	iconst_0
				90	bipush		7
				92	iastore
				93	dup
				94	iconst_1
				95	bipush		8
				97	iastore
				98	aastore
				99	aastore
				100	putfield	cp index #10 (Field sketch/Sketch.matrix3d, descriptor: [[[I)
				103	aload_0
				104	iconst_3
				105	anewarray	cp index #11 (class: [D)
				108	dup
				109	iconst_0
				110	iconst_3
				111	newarray	7 (array of double)
				113	dup
				114	iconst_0
				115	ldc2_w		cp index #115 (double: 1.234560e+002)
				118	dastore
				119	dup
				120	iconst_1
				121	ldc2_w		cp index #121 (double: -6.543210e+002)
				124	dastore
				125	dup
				126	iconst_2
				127	ldc2_w		cp index #127 (double: 9.876543e+008)
				130	dastore
				131	aastore
				132	dup
				133	iconst_1
				134	iconst_3
				135	newarray	7 (array of double)
				137	dup
				138	iconst_0
				139	ldc2_w		cp index #139 (double: 1.797693e+308)
				142	dastore
				143	dup
				144	iconst_1
				145	ldc2_w		cp index #145 (double: 4.940656e-324)
				148	dastore
				149	dup
				150	iconst_2
				151	ldc2_w		cp index #151 (double: 2.225074e-308)
				154	dastore
				155	aastore
				156	dup
				157	iconst_2
				158	iconst_3
				159	newarray	7 (array of double)
				161	dup
				162	iconst_0
				163	ldc2_w		cp index #163 (double: nan)
				166	dastore
				167	dup
				168	iconst_1
				169	ldc2_w		cp index #169 (double: inf)
				172	dastore
				173	dup
				174	iconst_2
				175	ldc2_w		cp index #175 (double: -inf)
				178	dastore
				179	aastore
				180	putfield	cp index #31 (Field sketch/Sketch.matrix2d, descriptor: [[D)
				183	return

			Code Attribute #1 - LineNumberTable:

				line_number_table_length: 7

				Table:	Index	line_number	start_pc
					1	6		0
					2	13		4
					3	16		11
					4	17		17
					5	19		22
					6	26		103
					7	40		183


	Method #2:

		name_index:        cp index #81 <mymethod>
		descriptor_index:  cp index #82 <(IJ)V>
		access_flags:      0x0001 [public]
		attribute_count:   1

		Method Attribute #1 - Code:

			max_stack: 4, max_locals: 6, code_length: 35
			exception_table_length: 0, attribute_count: 1

			Code:	Offset	Mnemonic	Parameters
				0	iconst_2
				1	newarray	10 (array of int)
				3	astore		4
				5	new		cp index #32 (class: sketch/Sketch$NestedClass)
				8	dup
				9	aload_0
				10	invokespecial	cp index #33 (Method sketch/Sketch$NestedClass.<init>, descriptor: (Lsketch/Sketch;)V)
				13	astore		5
				15	aload		4
				17	iconst_0
				18	aload		5
				20	aload		4
				22	invokeinterface	cp index #34, count: 2 (InterfaceMethod sketch/Sketch$Test.method1, descriptor: ([I)I)
				27	iastore
				28	lload_2
				29	getstatic	cp index #35 (Field sketch/Sketch.long_static_value, descriptor: J)
				32	ladd
				33	lstore_2
				34	return

			Code Attribute #1 - LineNumberTable:

				line_number_table_length: 5

				Table:	Index	line_number	start_pc
					1	47		0
					2	48		5
					3	50		15
					4	51		28
					5	52		34


	Method #3:

		name_index:        cp index #83 <add_10>
		descriptor_index:  cp index #84 <(IF)J>
		access_flags:      0x0001 [public]
		attribute_count:   2

		Method Attribute #1 - Code:

			max_stack: 4, max_locals: 5, code_length: 17
			exception_table_length: 0, attribute_count: 1

			Code:	Offset	Mnemonic	Parameters
				0	iinc		1, 5
				3	iload_1
				4	i2l
				5	fload_2
				6	f2l
				7	ladd
				8	lstore_3
				9	lload_3
				10	ldc2_w		cp index #10 (long: 5)
				13	ladd
				14	lstore_3
				15	lload_3
				16	lreturn

			Code Attribute #1 - LineNumberTable:

				line_number_table_length: 4

				Table:	Index	line_number	start_pc
					1	55		0
					2	56		3
					3	57		9
					4	58		15


		Method Attribute #2 - Exceptions:

			number_of_exceptions: 1

				Exception #1: cp index #86 <java/lang/Error>


	Method #4:

		name_index:        cp index #87 <main>
		descriptor_index:  cp index #88 <([Ljava/lang/String;)V>
		access_flags:      0x0009 [public, static]
		attribute_count:   1

		Method Attribute #1 - Code:

			max_stack: 2, max_locals: 6, code_length: 41
			exception_table_length: 1, attribute_count: 2

			Code:	Offset	Mnemonic	Parameters
				0	ldc		cp index #0 (string: ola)
				2	astore_1
				3	aload_1
				4	instanceof	cp index #39 (class: java/lang/String)
				7	ifeq			13
				10	getstatic	cp index #40 (Field java/lang/System.out, descriptor: Ljava/io/PrintStream;)
				13	aload_1
				14	checkcast	cp index #39 (class: java/lang/String)
				17	invokevirtual	cp index #41 (Method java/io/PrintStream.println, descriptor: (Ljava/lang/String;)V)
				20	iconst_2
				21	iconst_2
				22	multianewarray	cp index #42, dimension 2 (class: [[Ljava/lang/String;)
				26	astore_2
				27	iconst_0
				28	istore_3
				29	bipush		62
				31	iload_3
				32	idiv
				33	istore		4
				35	goto			5
				38	astore		5
				40	return

			Exception Table:
			Index	start_pc	end_pc	handler_pc	catch_type
			1	27		35	38		43 <java/lang/ArithmeticException>

			Code Attribute #1 - LineNumberTable:

				line_number_table_length: 9

				Table:	Index	line_number	start_pc
					1	62		0
					2	64		3
					3	65		10
					4	68		20
					5	72		27
					6	73		29
					7	75		35
					8	74		38
					9	76		40

			Code Attribute #2 - StackMapTable:
				Attribute not implemented and ignored.


	Method #5:

		name_index:        cp index #93 <<clinit>>
		descriptor_index:  cp index #78 <()V>
		access_flags:      0x0008 [static]
		attribute_count:   1

		Method Attribute #1 - Code:

			max_stack: 4, max_locals: 0, code_length: 33
			exception_table_length: 0, attribute_count: 1

			Code:	Offset	Mnemonic	Parameters
				0	iconst_5
				1	newarray	10 (array of int)
				3	dup
				4	iconst_0
				5	iconst_1
				6	iastore
				7	dup
				8	iconst_1
				9	iconst_2
				10	iastore
				11	dup
				12	iconst_2
				13	iconst_3
				14	iastore
				15	dup
				16	iconst_3
				17	iconst_4
				18	iastore
				19	dup
				20	iconst_4
				21	iconst_5
				22	iastore
				23	putstatic	cp index #44 (Field sketch/Sketch.values, descriptor: [I)
				26	ldc2_w		cp index #26 (long: 98765432123456789)
				29	putstatic	cp index #35 (Field sketch/Sketch.long_static_value, descriptor: J)
				32	return

			Code Attribute #1 - LineNumberTable:

				line_number_table_length: 2

				Table:	Index	line_number	start_pc
					1	8		0
					2	14		26


---- Class Attributes ----

	Attribute #1 - SourceFile:

		sourcefile_index: #95 <Sketch.java>


	Attribute #2 - InnerClasses:

		number_of_classes: 3

		Inner Class #1:

			inner_class_info_index:   cp index #32 <sketch/Sketch$NestedClass>
			outer_class_info_index:   cp index #47 <sketch/Sketch>
			inner_name_index:         cp index #51 <NestedClass>
			inner_class_access_flags: 0x0000 [no flags]

		Inner Class #2:

			inner_class_info_index:   cp index #53 <sketch/Sketch$AnotherInterface>
			outer_class_info_index:   cp index #47 <sketch/Sketch>
			inner_name_index:         cp index #54 <AnotherInterface>
			inner_class_access_flags: 0x0608 [abstract, static, interface]

		Inner Class #3:

			inner_class_info_index:   cp index #55 <sketch/Sketch$Test>
			outer_class_info_index:   cp index #47 <sketch/Sketch>
			inner_name_index:         cp index #56 <Test>
			inner_class_access_flags: 0x0608 [abstract, static, interface]
